{
  "db_name": "PostgreSQL",
  "query": "SELECT faction_id, name FROM faction WHERE faction_id = ANY($1)",
  "describe": {
    "columns": [
      {
        "ordinal": 0,
        "name": "faction_id",
        "type_info": "Int2"
      },
      {
        "ordinal": 1,
        "name": "name",
        "type_info": "Varchar"
      }
    ],
    "parameters": {
      "Left": [
        "Int2Array"
      ]
    },
    "nullable": [
      false,
      true
    ]
  },
  "hash": "d66cf855be2055a3aa7fe1eb79158eed5a74f2712e0c07ef0afc9e04dac5dc6c"
}
